{
  "class": "12",
  "subject": "Business Studies",
  "chapter": "Financial Management",
  "content_type": "formula_sheet",
  "generated_by": "groq/llama-3.3-70b-versatile",
  "generated_at": "2026-06-30T18:00:55.411Z",
  "version": "1.0",
  "data": {
    "formulas": [
      {
        "name": "1. Earnings Per Share (EPS)",
        "formula": "EPS = (Net Profit - Preference Share Dividend) / Number of Equity Shares",
        "variables": "Net Profit, Preference Share Dividend, Number of Equity Shares",
        "units": "Rupees",
        "notes": "To calculate the profit earned by the company on each equity share"
      },
      {
        "name": "2. Dividend Per Share",
        "formula": "Dividend Per Share = (Total Dividend / Number of Equity Shares)",
        "variables": "Total Dividend, Number of Equity Shares",
        "units": "Rupees",
        "notes": "To calculate the dividend paid to each equity shareholder"
      },
      {
        "name": "3. Return on Investment (ROI) or Return on Equity (ROE)",
        "formula": "ROI/ROE = (Net Profit / Total Investment or Shareholders' Funds) * 100",
        "variables": "Net Profit, Total Investment or Shareholders' Funds",
        "units": "Percentage",
        "notes": "To evaluate the return generated by the investment"
      },
      {
        "name": "4. Debt-Equity Ratio",
        "formula": "Debt-Equity Ratio = Total Debt / Total Shareholders' Funds",
        "variables": "Total Debt, Total Shareholders' Funds",
        "units": "Ratio",
        "notes": "To assess the company's leverage and financial risk"
      },
      {
        "name": "5. Current Ratio",
        "formula": "Current Ratio = Current Assets / Current Liabilities",
        "variables": "Current Assets, Current Liabilities",
        "units": "Ratio",
        "notes": "To evaluate the company's liquidity and ability to meet short-term obligations"
      },
      {
        "name": "6. Quick Ratio or Acid Test Ratio",
        "formula": "Quick Ratio = (Current Assets - Inventory) / Current Liabilities",
        "variables": "Current Assets, Inventory, Current Liabilities",
        "units": "Ratio",
        "notes": "To assess the company's ability to meet short-term obligations without relying on inventory"
      },
      {
        "name": "7. Capital Gearing Ratio",
        "formula": "Capital Gearing Ratio = (Preference Share Capital + Debentures + Long-term Loans) / (Equity Share Capital + Reserves and Surplus)",
        "variables": "Preference Share Capital, Debentures, Long-term Loans, Equity Share Capital, Reserves and Surplus",
        "units": "Ratio",
        "notes": "To evaluate the company's capital structure and financial leverage"
      },
      {
        "name": "8. Interest Coverage Ratio",
        "formula": "Interest Coverage Ratio = Earnings Before Interest and Taxes (EBIT) / Interest on Debt",
        "variables": "EBIT, Interest on Debt",
        "units": "Ratio",
        "notes": "To assess the company's ability to meet interest payments on its debt"
      },
      {
        "name": "9. Operating Profit Ratio",
        "formula": "Operating Profit Ratio = (Operating Profit / Net Sales) * 100",
        "variables": "Operating Profit, Net Sales",
        "units": "Percentage",
        "notes": "To evaluate the company's operating efficiency and profitability"
      },
      {
        "name": "10. Net Profit Ratio",
        "formula": "Net Profit Ratio = (Net Profit / Net Sales) * 100",
        "variables": "Net Profit, Net Sales",
        "units": "Percentage",
        "notes": "To assess the company's overall profitability"
      }
    ]
  }
}