{
  "class": "11",
  "subject": "Physical Education",
  "chapter": "Physical Activity and Leadership Training",
  "content_type": "detailed_notes",
  "generated_by": "groq/llama-3.1-8b-instant",
  "generated_at": "2026-06-25T03:18:39.171+00:00",
  "version": "1.0",
  "data": {
    "markdown": "# Physical Activity and Leadership Training\n## 📌 Chapter Overview\n\nThis chapter focuses on the importance of physical activity and leadership training in the development of an individual. Physical activity not only contributes to physical fitness but also has a significant impact on mental and emotional well-being. Effective leadership is essential in various aspects of life, including sports, education, and the workforce. This chapter aims to equip students with the knowledge and skills required to become effective leaders and to understand the significance of physical activity in promoting overall well-being.\n\nLeadership training is a critical aspect of physical education, as it enables individuals to develop the necessary skills to motivate and guide others. This chapter explores the various aspects of leadership, including leadership styles, communication, and problem-solving. The chapter also emphasizes the importance of physical activity in promoting physical fitness, mental health, and social skills.\n\nThe chapter is divided into several sections, each focusing on a specific aspect of physical activity and leadership training. Through a combination of theoretical knowledge and practical applications, students will gain a comprehensive understanding of the subject matter.\n\n## 🎯 Learning Objectives\n\n* Understand the importance of physical activity in promoting physical fitness, mental health, and social skills\n* Identify the key characteristics of effective leadership\n* Analyze the different leadership styles and their applications\n* Develop communication and problem-solving skills\n* Understand the role of physical activity in promoting social skills and teamwork\n* Evaluate the impact of physical activity on mental health and well-being\n* Develop a leadership plan and implement it in a practical setting\n* Analyze the role of physical education in promoting leadership skills\n* Understand the importance of self-reflection and self-assessment in leadership development\n\n## 🔑 Key Concepts & Definitions\n\n* **Physical Activity**: Any form of voluntary movement that is undertaken for the purpose of promoting physical fitness, recreation, or competition.\n* **Leadership**: The process of influencing and guiding others to achieve a common goal or objective.\n* **Leadership Style**: The way in which a leader interacts and influences their followers, including their communication style, decision-making process, and problem-solving approach.\n* **Communication**: The process of exchanging information, ideas, and opinions between individuals or groups.\n* **Problem-Solving**: The process of identifying, analyzing, and resolving problems or challenges.\n* **Physical Fitness**: The ability to perform physical tasks and activities with ease and efficiency.\n* **Mental Health**: The state of being mentally healthy and well, characterized by a positive outlook, emotional stability, and effective coping mechanisms.\n\n## 📐 Core Theory & Principles\n\n* **Social Learning Theory**: This theory proposes that individuals learn new behaviors and skills by observing and imitating others.\n* **Self-Efficacy Theory**: This theory suggests that individuals' confidence and motivation to perform a task are influenced by their perceived ability to perform it.\n* **Maslow's Hierarchy of Needs**: This theory proposes that individuals have different levels of needs, including physiological, safety, love, esteem, and self-actualization needs.\n* **Herzberg's Two-Factor Theory**: This theory proposes that job satisfaction is influenced by two factors: motivators (such as recognition and achievement) and hygiene factors (such as salary and working conditions).\n\n## 🧮 Important Formulas & Laws\n\n* **No specific formulas or laws are applicable to this chapter.**\n\n## 🔬 Detailed Explanations\n\n### Leadership Styles\n\nThere are several leadership styles, including:\n\n* **Autocratic Leadership**: A style of leadership in which the leader makes all the decisions and expects obedience from their followers.\n* **Democratic Leadership**: A style of leadership in which the leader involves their followers in the decision-making process and encourages their input and participation.\n* **Laissez-Faire Leadership**: A style of leadership in which the leader gives their followers a great deal of autonomy and freedom to make their own decisions.\n\n### Communication\n\nEffective communication is critical to leadership, and involves:\n\n* **Verbal Communication**: The exchange of information through spoken words.\n* **Nonverbal Communication**: The exchange of information through body language, facial expressions, and other nonverbal cues.\n* **Written Communication**: The exchange of information through written messages, such as emails and reports.\n\n### Problem-Solving\n\nEffective problem-solving involves:\n\n* **Identifying the Problem**: Recognizing the problem or challenge and defining it clearly.\n* **Analyzing the Problem**: Gathering information and data to understand the problem and its causes.\n* **Generating Solutions**: Identifying potential solutions and evaluating their feasibility.\n* **Implementing the Solution**: Selecting the best solution and implementing it.\n\n## 🖼️ Diagrams & Visual Concepts\n\n* **Leadership Styles Diagram**: A diagram showing the different leadership styles, including autocratic, democratic, and laissez-faire leadership.\n* **Communication Process Diagram**: A diagram showing the different stages of communication, including sending, receiving, and interpreting messages.\n* **Problem-Solving Model**: A diagram showing the different stages of problem-solving, including identifying, analyzing, generating, and implementing solutions.\n\n## ⭐ Most Important Points (Exam Focus)\n\n* Leadership is a process of influencing and guiding others to achieve a common goal or objective.\n* There are several leadership styles, including autocratic, democratic, and laissez-faire leadership.\n* Effective communication is critical to leadership and involves verbal, nonverbal, and written communication.\n* Problem-solving involves identifying, analyzing, generating, and implementing solutions.\n* Leadership development involves self-reflection, self-assessment, and continuous learning.\n* Physical activity promotes physical fitness, mental health, and social skills.\n* Physical education plays a critical role in promoting leadership skills.\n\n## ❌ Common Mistakes to Avoid\n\n* Confusing leadership with management.\n* Assuming that leadership is a natural ability, rather than a skill that can be developed.\n* Failing to communicate effectively with followers.\n* Ignoring the importance of self-reflection and self-assessment in leadership development.\n* Assuming that physical activity is only for physical fitness, rather than for mental health and social skills.\n\n## 💡 Real-World Applications\n\n* **Sports Leadership**: Effective leadership is critical in sports, where teams need to work together to achieve a common goal.\n* **Education Leadership**: Effective leadership is critical in education, where teachers need to motivate and guide their students to achieve academic success.\n* **Workplace Leadership**: Effective leadership is critical in the workplace, where managers need to motivate and guide their employees to achieve organizational goals.\n* **Community Leadership**: Effective leadership is critical in communities, where leaders need to work with stakeholders to develop and implement community projects.\n* **Health Leadership**: Effective leadership is critical in healthcare, where leaders need to motivate and guide healthcare professionals to provide high-quality patient care.\n\n## 🔁 Quick Revision Summary\n\n* Leadership is a process of influencing and guiding others to achieve a common goal or objective.\n* There are several leadership styles, including autocratic, democratic, and laissez-faire leadership.\n* Effective communication is critical to leadership and involves verbal, nonverbal, and written communication.\n* Problem-solving involves identifying, analyzing, generating, and implementing solutions.\n* Leadership development involves self-reflection, self-assessment, and continuous learning.\n* Physical activity promotes physical fitness, mental health, and social skills.\n* Physical education plays a critical role in promoting leadership skills.\n* Leadership is not a natural ability, but a skill that can be developed.\n* Effective leadership involves empathy, self-awareness, and emotional intelligence.\n* Leadership development involves a growth mindset and a willingness to learn."
  }
}