{
  "class": "12",
  "subject": "Accountancy",
  "chapter": "Reconstitution of Partnership: Retirement & Death",
  "content_type": "detailed_notes",
  "generated_by": "groq/llama-3.1-8b-instant",
  "generated_at": "2026-06-30T16:12:24.206Z",
  "version": "1.0",
  "data": {
    "markdown": "# Reconstitution of Partnership: Retirement & Death - DETAILED NOTES\n\n## Introduction\n\nThe concept of reconstitution of partnership is an essential aspect of partnership accounting, which deals with the changes that occur in a partnership firm due to various reasons such as retirement of a partner, death of a partner, or admission of a new partner. These changes can significantly impact the rights and interests of the remaining partners in the firm.\n\nReconstitution of partnership involves the process of adjusting the capital accounts, profit and loss accounts, and other related accounts to reflect the new ownership structure and capital contributions of the partners.\n\n## What is Reconstitution of Partnership?\n\nReconstitution of partnership refers to the process of adjusting the books of a partnership firm to reflect the changes in the ownership structure, capital contributions, and profit-sharing ratio due to the retirement or death of a partner.\n\n## Components / Sub-topics\n\n### **Retirement of a Partner**\n\n#### Definition\n\nRetirement of a partner refers to the voluntary withdrawal of a partner from the partnership firm.\n\n#### Characteristics\n\n* The retiring partner's share of profits and losses is adjusted in the capital accounts.\n* The remaining partners' share of profits and losses is adjusted proportionately.\n* The retiring partner's share of assets and liabilities is adjusted in the capital accounts.\n\n#### Sub-types\n\n| Type of Retirement | Characteristics |\n| --- | --- |\n| Voluntary Retirement | Partner's decision to retire from the firm. |\n| Compulsory Retirement | Partner is forced to retire from the firm due to certain circumstances. |\n\n### **Death of a Partner**\n\n#### Definition\n\nDeath of a partner refers to the passing away of a partner in the partnership firm.\n\n#### Characteristics\n\n* The deceased partner's share of profits and losses is adjusted in the capital accounts.\n* The remaining partners' share of profits and losses is adjusted proportionately.\n* The deceased partner's share of assets and liabilities is adjusted in the capital accounts.\n\n#### Sub-types\n\n| Type of Death | Characteristics |\n| --- | --- |\n| Sudden Death | Partner dies suddenly, and their share of profits and losses is adjusted. |\n| Anticipated Death | Partner's death is anticipated, and their share of profits and losses is adjusted accordingly. |\n\n## Retirement of a Partner\n\nWhen a partner retires from the partnership firm, the following steps are taken:\n\n1.  **Adjustment of Capital Accounts**: The retiring partner's share of capital is adjusted in their capital account, and the remaining partners' share of capital is adjusted proportionately.\n2.  **Adjustment of Profit and Loss Accounts**: The retiring partner's share of profits and losses is adjusted in their capital account, and the remaining partners' share of profits and losses is adjusted proportionately.\n3.  **Adjustment of Assets and Liabilities**: The retiring partner's share of assets and liabilities is adjusted in their capital account.\n\nExample:\n\nA and B are partners in a firm with a profit-sharing ratio of 3:2. A retires from the firm, and the remaining assets are valued at Rs. 1,00,000. The capital account of A shows a balance of Rs. 30,000, and the capital account of B shows a balance of Rs. 20,000. The profit and loss account shows a balance of Rs. 10,000.\n\nAfter A's retirement, the capital account of A is adjusted as follows:\n\n| Debit | Credit |\n| --- | --- |\n| To A's Capital A/c | Rs. 30,000 |\n\nThe capital account of B is adjusted as follows:\n\n| Debit | Credit |\n| --- | --- |\n| To B's Capital A/c | Rs. 20,000 |\n| To A's Capital A/c | Rs. 10,000 |\n\nThe profit and loss account is adjusted as follows:\n\n| Debit | Credit |\n| --- | --- |\n| To B's Capital A/c | Rs. 6,667 (2/5 × 10,000) |\n| To A's Capital A/c | Rs. 3,333 (3/5 × 10,000)\n\n## Death of a Partner\n\nWhen a partner dies, the following steps are taken:\n\n1.  **Adjustment of Capital Accounts**: The deceased partner's share of capital is adjusted in their capital account, and the remaining partners' share of capital is adjusted proportionately.\n2.  **Adjustment of Profit and Loss Accounts**: The deceased partner's share of profits and losses is adjusted in their capital account, and the remaining partners' share of profits and losses is adjusted proportionately.\n3.  **Adjustment of Assets and Liabilities**: The deceased partner's share of assets and liabilities is adjusted in their capital account.\n\nExample:\n\nA and B are partners in a firm with a profit-sharing ratio of 3:2. A dies, and the remaining assets are valued at Rs. 1,00,000. The capital account of A shows a balance of Rs. 30,000, and the capital account of B shows a balance of Rs. 20,000. The profit and loss account shows a balance of Rs. 10,000.\n\nAfter A's death, the capital account of A is adjusted as follows:\n\n| Debit | Credit |\n| --- | --- |\n| To A's Estate | Rs. 30,000 |\n\nThe capital account of B is adjusted as follows:\n\n| Debit | Credit |\n| --- | --- |\n| To B's Capital A/c | Rs. 20,000 |\n| To A's Estate | Rs. 10,000 |\n\nThe profit and loss account is adjusted as follows:\n\n| Debit | Credit |\n| --- | --- |\n| To B's Capital A/c | Rs. 6,667 (2/4 × 10,000) |\n| To A's Estate | Rs. 3,333 (1/4 × 10,000)\n\n## Conclusion\n\nReconstitution of partnership involves the process of adjusting the capital accounts, profit and loss accounts, and other related accounts to reflect the new ownership structure and capital contributions of the partners. Retirement and death of a partner are two significant events that lead to reconstitution of partnership.\n\nIn both cases, the capital accounts, profit and loss accounts, and assets and liabilities are adjusted to reflect the new ownership structure and capital contributions of the partners. The process of reconstitution of partnership is essential to ensure that the rights and interests of the remaining partners are protected and that the firm's assets and liabilities are properly accounted for."
  }
}