{
  "class": "11",
  "subject": "English",
  "chapter": "Ranga's Marriage",
  "content_type": "assertion_reason",
  "generated_by": "groq/llama-3.1-8b-instant",
  "generated_at": "2026-06-24T16:20:58.527Z",
  "version": "1.0",
  "data": {
    "questions": [
      {
        "assertion": "Assertion (A): Ranga's father was a wealthy man.",
        "reason": "Reason (R): His occupation as a minister suggests his financial stability.",
        "opts": [
          "(A) Both A and R are true and R is the correct explanation of A",
          "(B) Both A and R are true but R is not the correct explanation of A",
          "(C) A is true but R is false",
          "(D) A is false but R is true"
        ],
        "ans": "A",
        "explanation": "The occupation of a minister is typically associated with a high salary and financial stability, making option A true and reason R a correct explanation."
      },
      {
        "assertion": "Assertion (A): Ranga's father was a high-ranking government official.",
        "reason": "Reason (R): He was referred to as 'Doraiswamy Iyengar' which is a title of respect for high-ranking officials.",
        "opts": [
          "(A) Both A and R are true and R is the correct explanation of A",
          "(B) Both A and R are true but R is not the correct explanation of A",
          "(C) A is true but R is false",
          "(D) A is false but R is true"
        ],
        "ans": "A",
        "explanation": "The title 'Doraiswamy Iyengar' is a sign of respect in Indian culture, often given to high-ranking government officials, making option A true and reason R a correct explanation."
      },
      {
        "assertion": "Assertion (A): Rukmini's family was not pleased with her decision to marry Ranga.",
        "reason": "Reason (R): They considered him to be unsuitable for her due to his low social status.",
        "opts": [
          "(A) Both A and R are true and R is the correct explanation of A",
          "(B) Both A and R are true but R is not the correct explanation of A",
          "(C) A is true but R is false",
          "(D) A is false but R is true"
        ],
        "ans": "C",
        "explanation": "Rukmini's family was not pleased with her decision, but the reason was not necessarily Ranga's low social status, making option A true but reason R false."
      },
      {
        "assertion": "Assertion (A): Ranga's marriage to Rukmini was a love marriage.",
        "reason": "Reason (R): They chose each other as their life partners.",
        "opts": [
          "(A) Both A and R are true and R is the correct explanation of A",
          "(B) Both A and R are true but R is not the correct explanation of A",
          "(C) A is true but R is false",
          "(D) A is false but R is true"
        ],
        "ans": "A",
        "explanation": "Ranga and Rukmini chose each other as their life partners, which is a common characteristic of love marriages, making option A true and reason R a correct explanation."
      },
      {
        "assertion": "Assertion (A): Rukmini's family was a traditional family.",
        "reason": "Reason (R): They followed the traditional norms of arranged marriages.",
        "opts": [
          "(A) Both A and R are true and R is the correct explanation of A",
          "(B) Both A and R are true but R is not the correct explanation of A",
          "(C) A is true but R is false",
          "(D) A is false but R is true"
        ],
        "ans": "B",
        "explanation": "Rukmini's family followed traditional norms, but the reason was not necessarily the traditional norms of arranged marriages, making option A true but reason R false."
      },
      {
        "assertion": "Assertion (A): Ranga's family was a modern family.",
        "reason": "Reason (R): They accepted Rukmini as their daughter-in-law.",
        "opts": [
          "(A) Both A and R are true and R is the correct explanation of A",
          "(B) Both A and R are true but R is not the correct explanation of A",
          "(C) A is true but R is false",
          "(D) A is false but R is true"
        ],
        "ans": "A",
        "explanation": "Ranga's family accepted Rukmini as their daughter-in-law, which is a characteristic of modern families, making option A true and reason R a correct explanation."
      },
      {
        "assertion": "Assertion (A): Rukmini was a traditional girl.",
        "reason": "Reason (R): She was brought up in a traditional household.",
        "opts": [
          "(A) Both A and R are true and R is the correct explanation of A",
          "(B) Both A and R are true but R is not the correct explanation of A",
          "(C) A is true but R is false",
          "(D) A is false but R is true"
        ],
        "ans": "C",
        "explanation": "Rukmini was brought up in a traditional household, but the reason was not necessarily that she was a traditional girl, making option A true but reason R false."
      },
      {
        "assertion": "Assertion (A): Ranga's marriage to Rukmini was a happy marriage.",
        "reason": "Reason (R): They were deeply in love with each other.",
        "opts": [
          "(A) Both A and R are true and R is the correct explanation of A",
          "(B) Both A and R are true but R is not the correct explanation of A",
          "(C) A is true but R is false",
          "(D) A is false but R is true"
        ],
        "ans": "A",
        "explanation": "Ranga and Rukmini were deeply in love with each other, which is a common characteristic of happy marriages, making option A true and reason R a correct explanation."
      },
      {
        "assertion": "Assertion (A): Rukmini's decision to marry Ranga was a wise decision.",
        "reason": "Reason (R): She chose him as her life partner after careful consideration.",
        "opts": [
          "(A) Both A and R are true and R is the correct explanation of A",
          "(B) Both A and R are true but R is not the correct explanation of A",
          "(C) A is true but R is false",
          "(D) A is false but R is true"
        ],
        "ans": "A",
        "explanation": "Rukmini chose Ranga as her life partner after careful consideration, which is a sign of a wise decision, making option A true and reason R a correct explanation."
      }
    ],
    "total": 9
  }
}