{
  "class": "11",
  "subject": "Physics",
  "chapter": "Mechanical Properties of Fluids",
  "content_type": "ncert_summary",
  "generated_by": "groq/llama-3.1-8b-instant",
  "generated_at": "2026-06-24T15:15:46.270Z",
  "version": "1.0",
  "data": {
    "markdown": "# NCERT Summary: Mechanical Properties of Fluids\n\n## Chapter at a Glance\nThe chapter on Mechanical Properties of Fluids explains the behavior of fluids under various conditions, including the properties of fluid pressure, fluid flow, and the forces acting on a fluid. It covers the principles of fluid dynamics and the behavior of fluids in different states, such as static fluids and flowing fluids. The chapter also discusses the concept of viscosity and the relationship between fluid pressure and density. The study of fluid mechanics is crucial in understanding various natural phenomena and engineering applications.\n\n## Section-wise Summary\n\n### 8.1 Introduction\nThe chapter begins with the introduction to fluid mechanics, which is the study of the behavior of fluids under various conditions. Fluids are substances that have no fixed shape and can flow freely. The chapter explains the importance of fluid mechanics in various fields, such as engineering, physics, and everyday life.\n\n### 8.2 Pressure in a Fluid\nThis section discusses the concept of pressure in a fluid, which is the force exerted per unit area on the surface of an object or on the walls of a container. The pressure at a point in a fluid is given by the formula P = ρgh, where ρ is the density of the fluid, g is the acceleration due to gravity, and h is the height of the fluid column above the point. The chapter also explains the concept of atmospheric pressure and its effect on the pressure in a fluid.\n\n### 8.3 Pressure Measurement\nThis section discusses the various methods of measuring pressure, including the use of manometers, barometers, and pressure gauges. The chapter explains the principle of operation of these instruments and their limitations.\n\n### 8.4 Variation of Pressure with Depth\nThis section discusses the variation of pressure with depth in a fluid. The chapter explains the concept of hydrostatic pressure and the relationship between pressure and depth. The formula for hydrostatic pressure is given as P = ρgh, where ρ is the density of the fluid, g is the acceleration due to gravity, and h is the depth below the surface.\n\n### 8.5 Atmospheric Pressure and Its Variation\nThis section discusses the variation of atmospheric pressure with altitude, latitude, and time. The chapter explains the factors that affect atmospheric pressure and its relationship with weather phenomena.\n\n### 8.6 Compressibility of Fluids\nThis section discusses the compressibility of fluids, which is the ability of a fluid to change its volume under the influence of external pressure. The chapter explains the concept of elasticity and the relationship between compressibility and elasticity.\n\n### 8.7 Surface Tension\nThis section discusses the concept of surface tension, which is the property of a fluid that causes it to behave as if it has an \"elastic skin\" at its surface. The chapter explains the factors that affect surface tension and its relationship with the properties of the fluid.\n\n### 8.8 Viscosity\nThis section discusses the concept of viscosity, which is the property of a fluid that causes it to resist shear stress. The chapter explains the factors that affect viscosity and its relationship with the properties of the fluid.\n\n### 8.9 Streamline and Turbulent Flows\nThis section discusses the concept of fluid flow, which can be either streamline or turbulent. The chapter explains the characteristics of streamline and turbulent flow and their relationship with the properties of the fluid.\n\n### 8.10 Bernoulli's Theorem\nThis section discusses Bernoulli's theorem, which relates the pressure of a fluid to its velocity. The chapter explains the concept of potential energy and kinetic energy and their relationship with the pressure of a fluid.\n\n## Important NCERT Exercises Insight\n\n* Key concepts tested in NCERT exercises:\n + Pressure in a fluid\n + Variation of pressure with depth\n + Surface tension\n + Viscosity\n + Streamline and turbulent flows\n + Bernoulli's theorem\n* What to remember:\n + The formula for hydrostatic pressure is P = ρgh.\n + The concept of surface tension and its relationship with the properties of the fluid.\n + The concept of viscosity and its relationship with the properties of the fluid.\n + Bernoulli's theorem and its relationship with the pressure of a fluid.\n\n## NCERT Exemplar Focus\nThe NCERT Exemplar for this chapter covers additional topics such as:\n\n* The concept of fluid dynamics and its relationship with the properties of the fluid.\n* The concept of boundary layer and its relationship with fluid flow.\n* The concept of Reynolds number and its relationship with fluid flow.\n\n## Board Exam Relevance\nThe marks weightage for this chapter in the board exam is around 10-15%. The frequently asked topics from this chapter include:\n\n* Pressure in a fluid\n* Variation of pressure with depth\n* Surface tension\n* Viscosity\n* Streamline and turbulent flows\n* Bernoulli's theorem\n\nThe chapter on Mechanical Properties of Fluids is an essential part of the physics curriculum and is relevant to various fields, including engineering, physics, and everyday life. The study of fluid mechanics is crucial in understanding various natural phenomena and engineering applications."
  }
}